pyreloader.py
pyreloader-0.1.4.dist-info/LICENSE.txt
pyreloader-0.1.4.dist-info/METADATA
pyreloader-0.1.4.dist-info/WHEEL
pyreloader-0.1.4.dist-info/entry_points.txt
pyreloader-0.1.4.dist-info/top_level.txt
pyreloader-0.1.4.dist-info/RECORD
